setuptools_changelog_shortener.py
setuptools_changelog_shortener-0.2.0.dist-info/LICENSE
setuptools_changelog_shortener-0.2.0.dist-info/METADATA
setuptools_changelog_shortener-0.2.0.dist-info/WHEEL
setuptools_changelog_shortener-0.2.0.dist-info/entry_points.txt
setuptools_changelog_shortener-0.2.0.dist-info/top_level.txt
setuptools_changelog_shortener-0.2.0.dist-info/zip-safe
setuptools_changelog_shortener-0.2.0.dist-info/RECORD
