Metadata-Version: 2.1
Name: setuptools-changelog-shortener
Version: 0.2.0
Summary: "setuptools-changelog-shortener: add only newest changelog entries to long_description"
Home-page: https://github.com/fschulze/setuptools-changelog-shortener
Author: Florian Schulze
Author-email: mail@florian-schulze.net
License: MIT
Project-URL: Bug Tracker, https://github.com/fschulze/setuptools-changelog-shortener/issues
Project-URL: Source Code, https://github.com/fschulze/setuptools-changelog-shortener
Platform: UNKNOWN
Classifier: Development Status :: 4 - Beta
Classifier: Intended Audience :: Developers
Classifier: License :: OSI Approved :: MIT License
Classifier: Programming Language :: Python :: 3
Classifier: Programming Language :: Python :: 3 :: Only
Classifier: Programming Language :: Python :: 3.6
Classifier: Programming Language :: Python :: 3.7
Classifier: Programming Language :: Python :: 3.8
Classifier: Programming Language :: Python :: 3.9
Classifier: Topic :: System :: Software Distribution
Classifier: Topic :: Utilities
Requires-Python: >=3.6
License-File: LICENSE
Requires-Dist: setuptools (>=45)
Requires-Dist: tomli (>=1.0)
